[
  {
    "trend_arrow": "SINGLE_UP", 
    "display_time": "2016-10-18T15:34:00-07:00", 
    "noise": 1, 
    "system_time": "2016-10-18T21:27:37-07:00", 
    "direction": "SingleUp", 
    "sgv": 98, 
    "dateString": "2016-10-18T15:34:00-07:00", 
    "date": 1476830040000, 
    "unfiltered": 100336, 
    "filtered": 86064, 
    "device": "openaps://indy-e1/cgm", 
    "rssi": 183, 
    "type": "sgv", 
    "glucose": 98
  }, 
  {
    "trend_arrow": "45_UP", 
    "display_time": "2016-10-18T15:29:00-07:00", 
    "noise": 1, 
    "system_time": "2016-10-18T21:22:37-07:00", 
    "direction": "FortyFiveUp", 
    "sgv": 85, 
    "dateString": "2016-10-18T15:29:00-07:00", 
    "date": 1476829740000, 
    "unfiltered": 90816, 
    "filtered": 79728, 
    "device": "openaps://indy-e1/cgm", 
    "rssi": 186, 
    "type": "sgv", 
    "glucose": 85
  }
]