[
  {
    "trend_arrow": "45_UP", 
    "display_time": "2016-10-27T19:28:23-07:00", 
    "noise": 1, 
    "system_time": "2016-10-28T02:16:14-07:00", 
    "direction": "FortyFiveUp", 
    "sgv": 121, 
    "dateString": "2016-10-27T19:28:23-07:00", 
    "date": 1477621703000, 
    "unfiltered": 134944, 
    "filtered": 126336, 
    "device": "openaps://indy-e1/cgm", 
    "rssi": 205, 
    "type": "sgv", 
    "glucose": 121
  }, 
  {
    "trend_arrow": "45_UP", 
    "display_time": "2016-10-27T19:23:23-07:00", 
    "noise": 1, 
    "system_time": "2016-10-28T02:11:14-07:00", 
    "direction": "FortyFiveUp", 
    "sgv": 118, 
    "dateString": "2016-10-27T19:23:23-07:00", 
    "date": 1477621403000, 
    "unfiltered": 132000, 
    "filtered": 118704, 
    "device": "openaps://indy-e1/cgm", 
    "rssi": 198, 
    "type": "sgv", 
    "glucose": 118
  }
]