[
  {
    "trend_arrow": "FLAT", 
    "display_time": "2016-10-30T22:03:16-07:00", 
    "noise": 1, 
    "system_time": "2016-10-31T03:56:37-07:00", 
    "direction": "Flat", 
    "sgv": 96, 
    "dateString": "2016-10-30T22:03:16-07:00", 
    "date": 1477890196000, 
    "unfiltered": 96064, 
    "filtered": 95568, 
    "device": "openaps://indy-e1/cgm", 
    "rssi": 196, 
    "type": "sgv", 
    "glucose": 96
  }, 
  {
    "trend_arrow": "FLAT", 
    "display_time": "2016-10-30T21:58:16-07:00", 
    "noise": 1, 
    "system_time": "2016-10-31T03:51:37-07:00", 
    "direction": "Flat", 
    "sgv": 97, 
    "dateString": "2016-10-30T21:58:16-07:00", 
    "date": 1477889896000, 
    "unfiltered": 96800, 
    "filtered": 97536, 
    "device": "openaps://indy-e1/cgm", 
    "rssi": 203, 
    "type": "sgv", 
    "glucose": 97
  }
]