[
  {
    "trend_arrow": "FLAT", 
    "display_time": "2016-11-01T01:33:11-07:00", 
    "noise": 1, 
    "system_time": "2016-11-01T07:26:31-07:00", 
    "direction": "Flat", 
    "sgv": 145, 
    "dateString": "2016-11-01T01:33:11-07:00", 
    "date": 1477989191000, 
    "unfiltered": 125184, 
    "filtered": 119104, 
    "device": "openaps://indy-e1/cgm", 
    "rssi": 196, 
    "type": "sgv", 
    "glucose": 145
  }, 
  {
    "trend_arrow": "FLAT", 
    "display_time": "2016-11-01T01:28:11-07:00", 
    "noise": 1, 
    "system_time": "2016-11-01T07:21:31-07:00", 
    "direction": "Flat", 
    "sgv": 139, 
    "dateString": "2016-11-01T01:28:11-07:00", 
    "date": 1477988891000, 
    "unfiltered": 120928, 
    "filtered": 116176, 
    "device": "openaps://indy-e1/cgm", 
    "rssi": 194, 
    "type": "sgv", 
    "glucose": 139
  }
]