[
  {
    "trend_arrow": "FLAT", 
    "display_time": "2016-10-28T17:43:18-07:00", 
    "noise": 1, 
    "system_time": "2016-10-29T00:31:10-07:00", 
    "direction": "Flat", 
    "sgv": 79, 
    "dateString": "2016-10-28T17:43:18-07:00", 
    "date": 1477701798000, 
    "unfiltered": 100192, 
    "filtered": 95680, 
    "device": "openaps://indy-e1/cgm", 
    "rssi": 186, 
    "type": "sgv", 
    "glucose": 79
  }, 
  {
    "trend_arrow": "45_UP", 
    "display_time": "2016-10-28T17:38:18-07:00", 
    "noise": 1, 
    "system_time": "2016-10-29T00:26:10-07:00", 
    "direction": "FortyFiveUp", 
    "sgv": 78, 
    "dateString": "2016-10-28T17:38:18-07:00", 
    "date": 1477701498000, 
    "unfiltered": 99440, 
    "filtered": 90976, 
    "device": "openaps://indy-e1/cgm", 
    "rssi": 186, 
    "type": "sgv", 
    "glucose": 78
  }
]