[
  {
    "trend_arrow": "FLAT", 
    "display_time": "2016-10-20T12:38:51-07:00", 
    "noise": 1, 
    "system_time": "2016-10-20T18:32:28-07:00", 
    "direction": "Flat", 
    "sgv": 116, 
    "dateString": "2016-10-20T12:38:51-07:00", 
    "date": 1476992331000, 
    "unfiltered": 115488, 
    "filtered": 118640, 
    "device": "openaps://indy-e1/cgm", 
    "rssi": 197, 
    "type": "sgv", 
    "glucose": 116
  }, 
  {
    "trend_arrow": "FLAT", 
    "display_time": "2016-10-20T12:33:51-07:00", 
    "noise": 1, 
    "system_time": "2016-10-20T18:27:27-07:00", 
    "direction": "Flat", 
    "sgv": 119, 
    "dateString": "2016-10-20T12:33:51-07:00", 
    "date": 1476992031000, 
    "unfiltered": 117312, 
    "filtered": 119024, 
    "device": "openaps://indy-e1/cgm", 
    "rssi": 195, 
    "type": "sgv", 
    "glucose": 119
  }
]