[
  {
    "trend_arrow": "FLAT", 
    "display_time": "2016-10-20T15:18:50-07:00", 
    "noise": 1, 
    "system_time": "2016-10-20T21:12:27-07:00", 
    "direction": "Flat", 
    "sgv": 96, 
    "dateString": "2016-10-20T15:18:50-07:00", 
    "date": 1477001930000, 
    "unfiltered": 101552, 
    "filtered": 102320, 
    "device": "openaps://indy-e1/cgm", 
    "rssi": 191, 
    "type": "sgv", 
    "glucose": 96
  }, 
  {
    "trend_arrow": "FLAT", 
    "display_time": "2016-10-20T15:13:51-07:00", 
    "noise": 1, 
    "system_time": "2016-10-20T21:07:27-07:00", 
    "direction": "Flat", 
    "sgv": 98, 
    "dateString": "2016-10-20T15:13:51-07:00", 
    "date": 1477001631000, 
    "unfiltered": 103408, 
    "filtered": 102592, 
    "device": "openaps://indy-e1/cgm", 
    "rssi": 198, 
    "type": "sgv", 
    "glucose": 98
  }
]