[
  {
    "trend_arrow": "FLAT", 
    "display_time": "2016-10-30T00:13:21-07:00", 
    "noise": 1, 
    "system_time": "2016-10-30T06:06:41-07:00", 
    "direction": "Flat", 
    "sgv": 118, 
    "dateString": "2016-10-30T00:13:21-07:00", 
    "date": 1477811601000, 
    "unfiltered": 126160, 
    "filtered": 126624, 
    "device": "openaps://indy-e1/cgm", 
    "rssi": 184, 
    "type": "sgv", 
    "glucose": 118
  }, 
  {
    "trend_arrow": "FLAT", 
    "display_time": "2016-10-30T00:08:21-07:00", 
    "noise": 1, 
    "system_time": "2016-10-30T06:01:41-07:00", 
    "direction": "Flat", 
    "sgv": 118, 
    "dateString": "2016-10-30T00:08:21-07:00", 
    "date": 1477811301000, 
    "unfiltered": 126080, 
    "filtered": 126064, 
    "device": "openaps://indy-e1/cgm", 
    "rssi": 191, 
    "type": "sgv", 
    "glucose": 118
  }
]