[
  {
    "trend_arrow": "NOT_COMPUTABLE", 
    "display_time": "2016-11-02T00:53:06-07:00", 
    "noise": 3, 
    "system_time": "2016-11-02T06:46:26-07:00", 
    "direction": "NOT COMPUTABLE", 
    "sgv": 57, 
    "dateString": "2016-11-02T00:53:06-07:00", 
    "date": 1478073186000, 
    "unfiltered": 49136, 
    "filtered": 29156, 
    "device": "openaps://indy-e1/cgm", 
    "rssi": 193, 
    "type": "sgv", 
    "glucose": 57
  }, 
  {
    "trend_arrow": "NOT_COMPUTABLE", 
    "display_time": "2016-11-02T00:48:06-07:00", 
    "noise": 3, 
    "system_time": "2016-11-02T06:41:26-07:00", 
    "direction": "NOT COMPUTABLE", 
    "sgv": 82, 
    "dateString": "2016-11-02T00:48:06-07:00", 
    "date": 1478072886000, 
    "unfiltered": 26804, 
    "filtered": 38288, 
    "device": "openaps://indy-e1/cgm", 
    "rssi": 189, 
    "type": "sgv", 
    "glucose": 82
  }
]