[
  {
    "trend_arrow": "FLAT", 
    "display_time": "2016-10-30T10:18:19-07:00", 
    "noise": 1, 
    "direction": "Flat", 
    "system_time": "2016-10-30T16:11:39-07:00", 
    "sgv": 125, 
    "dateString": "2016-10-30T10:18:19-07:00", 
    "device": "openaps://indy-e1/cgm", 
    "unfiltered": 130704, 
    "rssi": 186, 
    "date": 1477847899000.0, 
    "filtered": 130432, 
    "type": "sgv", 
    "glucose": 125
  }, 
  {
    "trend_arrow": "45_UP", 
    "display_time": "2016-10-30T10:13:19-07:00", 
    "noise": 1, 
    "direction": "FortyFiveUp", 
    "system_time": "2016-10-30T16:06:39-07:00", 
    "sgv": 126, 
    "dateString": "2016-10-30T10:13:19-07:00", 
    "device": "openaps://indy-e1/cgm", 
    "unfiltered": 131712, 
    "rssi": 206, 
    "date": 1477847599000.0, 
    "filtered": 123536, 
    "type": "sgv", 
    "glucose": 126
  }, 
  {
    "trend_arrow": "45_UP", 
    "display_time": "2016-10-30T10:08:19-07:00", 
    "noise": 1, 
    "direction": "FortyFiveUp", 
    "system_time": "2016-10-30T16:01:39-07:00", 
    "sgv": 124, 
    "dateString": "2016-10-30T10:08:19-07:00", 
    "device": "openaps://indy-e1/cgm", 
    "unfiltered": 130192, 
    "rssi": 185, 
    "date": 1477847299000.0, 
    "filtered": 115792, 
    "type": "sgv", 
    "glucose": 124
  }, 
  {
    "trend_arrow": "45_UP", 
    "display_time": "2016-10-30T10:03:19-07:00", 
    "noise": 1, 
    "direction": "FortyFiveUp", 
    "system_time": "2016-10-30T15:56:39-07:00", 
    "sgv": 117, 
    "dateString": "2016-10-30T10:03:19-07:00", 
    "device": "openaps://indy-e1/cgm", 
    "unfiltered": 124352, 
    "rssi": 197, 
    "date": 1477846999000.0, 
    "filtered": 110960, 
    "type": "sgv", 
    "glucose": 117
  }, 
  {
    "trend_arrow": "NOT_COMPUTABLE", 
    "display_time": "2016-10-30T09:58:19-07:00", 
    "noise": 1, 
    "direction": "NOT COMPUTABLE", 
    "system_time": "2016-10-30T15:51:39-07:00", 
    "sgv": 100, 
    "dateString": "2016-10-30T09:58:19-07:00", 
    "device": "openaps://indy-e1/cgm", 
    "unfiltered": 111552, 
    "rssi": 196, 
    "date": 1477846699000.0, 
    "filtered": 110144, 
    "type": "sgv", 
    "glucose": 100
  }, 
  {
    "trend_arrow": "NOT_COMPUTABLE", 
    "display_time": "2016-10-30T09:53:19-07:00", 
    "noise": 1, 
    "direction": "NOT COMPUTABLE", 
    "system_time": "2016-10-30T15:46:39-07:00", 
    "sgv": 95, 
    "dateString": "2016-10-30T09:53:19-07:00", 
    "device": "openaps://indy-e1/cgm", 
    "unfiltered": 107904, 
    "rssi": 194, 
    "date": 1477846399000.0, 
    "filtered": 111344, 
    "type": "sgv", 
    "glucose": 95
  }
]