[
  {
    "trend_arrow": "45_DOWN", 
    "display_time": "2016-10-26T09:13:30-07:00", 
    "noise": 1, 
    "direction": "FortyFiveDown", 
    "system_time": "2016-10-26T16:01:21-07:00", 
    "sgv": 170, 
    "dateString": "2016-10-26T09:13:30-07:00", 
    "device": "openaps://indy-e1/cgm", 
    "unfiltered": 171200, 
    "rssi": 180, 
    "date": 1477498410000.0, 
    "filtered": 185024, 
    "type": "sgv", 
    "glucose": 170
  }, 
  {
    "trend_arrow": "FLAT", 
    "display_time": "2016-10-26T09:08:30-07:00", 
    "noise": 1, 
    "direction": "Flat", 
    "system_time": "2016-10-26T15:56:21-07:00", 
    "sgv": 184, 
    "dateString": "2016-10-26T09:08:30-07:00", 
    "device": "openaps://indy-e1/cgm", 
    "unfiltered": 183648, 
    "rssi": 184, 
    "date": 1477498110000.0, 
    "filtered": 189664, 
    "type": "sgv", 
    "glucose": 184
  }, 
  {
    "trend_arrow": "FLAT", 
    "display_time": "2016-10-26T09:03:30-07:00", 
    "noise": 1, 
    "direction": "Flat", 
    "system_time": "2016-10-26T15:51:21-07:00", 
    "sgv": 191, 
    "dateString": "2016-10-26T09:03:30-07:00", 
    "device": "openaps://indy-e1/cgm", 
    "unfiltered": 189504, 
    "rssi": 182, 
    "date": 1477497810000.0, 
    "filtered": 193920, 
    "type": "sgv", 
    "glucose": 191
  }, 
  {
    "trend_arrow": "FLAT", 
    "display_time": "2016-10-26T08:58:30-07:00", 
    "noise": 1, 
    "direction": "Flat", 
    "system_time": "2016-10-26T15:46:21-07:00", 
    "sgv": 193, 
    "dateString": "2016-10-26T08:58:30-07:00", 
    "device": "openaps://indy-e1/cgm", 
    "unfiltered": 191552, 
    "rssi": 185, 
    "date": 1477497510000.0, 
    "filtered": 198592, 
    "type": "sgv", 
    "glucose": 193
  }, 
  {
    "trend_arrow": "FLAT", 
    "display_time": "2016-10-26T08:53:30-07:00", 
    "noise": 1, 
    "direction": "Flat", 
    "system_time": "2016-10-26T15:41:21-07:00", 
    "sgv": 196, 
    "dateString": "2016-10-26T08:53:30-07:00", 
    "device": "openaps://indy-e1/cgm", 
    "unfiltered": 194304, 
    "rssi": 200, 
    "date": 1477497210000.0, 
    "filtered": 202496, 
    "type": "sgv", 
    "glucose": 196
  }, 
  {
    "trend_arrow": "FLAT", 
    "display_time": "2016-10-26T08:48:30-07:00", 
    "noise": 1, 
    "direction": "Flat", 
    "system_time": "2016-10-26T15:36:22-07:00", 
    "sgv": 202, 
    "dateString": "2016-10-26T08:48:30-07:00", 
    "device": "openaps://indy-e1/cgm", 
    "unfiltered": 200256, 
    "rssi": 427, 
    "date": 1477496910000.0, 
    "filtered": 204256, 
    "type": "sgv", 
    "glucose": 202
  }
]