[
  {
    "trend_arrow": "45_DOWN", 
    "display_time": "2016-10-22T20:08:40-07:00", 
    "noise": 1, 
    "system_time": "2016-10-23T02:02:16-07:00", 
    "direction": "FortyFiveDown", 
    "sgv": 117, 
    "dateString": "2016-10-22T20:08:40-07:00", 
    "device": "openaps://indy-e1/cgm", 
    "unfiltered": 108928, 
    "rssi": 194, 
    "date": 1477192120000, 
    "filtered": 123280, 
    "type": "sgv", 
    "glucose": 117
  }, 
  {
    "trend_arrow": "45_DOWN", 
    "display_time": "2016-10-22T20:03:40-07:00", 
    "noise": 1, 
    "system_time": "2016-10-23T01:57:16-07:00", 
    "direction": "FortyFiveDown", 
    "sgv": 129, 
    "dateString": "2016-10-22T20:03:40-07:00", 
    "device": "openaps://indy-e1/cgm", 
    "unfiltered": 118128, 
    "rssi": 193, 
    "date": 1477191820000, 
    "filtered": 129456, 
    "type": "sgv", 
    "glucose": 129
  }
]