[
  {
    "trend_arrow": "45_DOWN", 
    "display_time": "2016-10-19T18:23:55-07:00", 
    "noise": 1, 
    "system_time": "2016-10-20T00:17:32-07:00", 
    "direction": "FortyFiveDown", 
    "sgv": 150, 
    "dateString": "2016-10-19T18:23:55-07:00", 
    "device": "openaps://indy-e1/cgm", 
    "unfiltered": 139296, 
    "rssi": 451, 
    "date": 1476926635000, 
    "filtered": 146304, 
    "type": "sgv", 
    "glucose": 150
  }, 
  {
    "trend_arrow": "SINGLE_DOWN", 
    "display_time": "2016-10-19T18:18:55-07:00", 
    "noise": 1, 
    "system_time": "2016-10-20T00:12:31-07:00", 
    "direction": "SingleDown", 
    "sgv": 151, 
    "dateString": "2016-10-19T18:18:55-07:00", 
    "device": "openaps://indy-e1/cgm", 
    "unfiltered": 140256, 
    "rssi": 196, 
    "date": 1476926335000, 
    "filtered": 156896, 
    "type": "sgv", 
    "glucose": 151
  }
]