[
  {
    "trend_arrow": "45_UP", 
    "display_time": "2016-10-26T11:18:29-07:00", 
    "noise": 1, 
    "system_time": "2016-10-26T18:06:21-07:00", 
    "direction": "FortyFiveUp", 
    "sgv": 106, 
    "dateString": "2016-10-26T11:18:29-07:00", 
    "device": "openaps://indy-e1/cgm", 
    "unfiltered": 112768, 
    "rssi": 175, 
    "date": 1477505909000, 
    "filtered": 103040, 
    "type": "sgv", 
    "glucose": 106
  }, 
  {
    "trend_arrow": "45_UP", 
    "display_time": "2016-10-26T11:13:29-07:00", 
    "noise": 1, 
    "system_time": "2016-10-26T18:01:21-07:00", 
    "direction": "FortyFiveUp", 
    "sgv": 100, 
    "dateString": "2016-10-26T11:13:29-07:00", 
    "device": "openaps://indy-e1/cgm", 
    "unfiltered": 106864, 
    "rssi": 186, 
    "date": 1477505609000, 
    "filtered": 97200, 
    "type": "sgv", 
    "glucose": 100
  }
]