[
  {
    "trend_arrow": "FLAT", 
    "system_time": "2016-10-18T20:02:37", 
    "noise": 1, 
    "direction": "Flat", 
    "sgv": 108, 
    "display_time": "2016-10-18T14:09:00", 
    "date": 1476824940000.0, 
    "dateString": "2016-10-18T14:09:00", 
    "unfiltered": 106992, 
    "filtered": 110192, 
    "device": "openaps://indy-e1/cgm", 
    "rssi": 188, 
    "type": "sgv", 
    "glucose": 108
  }, 
  {
    "trend_arrow": "FLAT", 
    "system_time": "2016-10-18T19:57:37", 
    "noise": 1, 
    "direction": "Flat", 
    "sgv": 113, 
    "display_time": "2016-10-18T14:04:00", 
    "date": 1476824640000.0, 
    "dateString": "2016-10-18T14:04:00", 
    "unfiltered": 110160, 
    "filtered": 112448, 
    "device": "openaps://indy-e1/cgm", 
    "rssi": 183, 
    "type": "sgv", 
    "glucose": 113
  }, 
  {
    "trend_arrow": "FLAT", 
    "system_time": "2016-10-18T19:52:37", 
    "noise": 1, 
    "direction": "Flat", 
    "sgv": 115, 
    "display_time": "2016-10-18T13:59:00", 
    "date": 1476824340000.0, 
    "dateString": "2016-10-18T13:59:00", 
    "unfiltered": 111616, 
    "filtered": 115296, 
    "device": "openaps://indy-e1/cgm", 
    "rssi": 186, 
    "type": "sgv", 
    "glucose": 115
  }, 
  {
    "trend_arrow": "FLAT", 
    "system_time": "2016-10-18T19:47:37", 
    "noise": 1, 
    "direction": "Flat", 
    "sgv": 117, 
    "display_time": "2016-10-18T13:54:00", 
    "date": 1476824040000.0, 
    "dateString": "2016-10-18T13:54:00", 
    "unfiltered": 113136, 
    "filtered": 117776, 
    "device": "openaps://indy-e1/cgm", 
    "rssi": 184, 
    "type": "sgv", 
    "glucose": 117
  }, 
  {
    "trend_arrow": "FLAT", 
    "system_time": "2016-10-18T19:42:37", 
    "noise": 1, 
    "direction": "Flat", 
    "sgv": 120, 
    "display_time": "2016-10-18T13:49:00", 
    "date": 1476823740000.0, 
    "dateString": "2016-10-18T13:49:00", 
    "unfiltered": 114784, 
    "filtered": 118528, 
    "device": "openaps://indy-e1/cgm", 
    "rssi": 181, 
    "type": "sgv", 
    "glucose": 120
  }, 
  {
    "trend_arrow": "FLAT", 
    "system_time": "2016-10-18T19:37:37", 
    "noise": 1, 
    "direction": "Flat", 
    "sgv": 126, 
    "display_time": "2016-10-18T13:44:01", 
    "date": 1476823441000.0, 
    "dateString": "2016-10-18T13:44:01", 
    "unfiltered": 118928, 
    "filtered": 116896, 
    "device": "openaps://indy-e1/cgm", 
    "rssi": 443, 
    "type": "sgv", 
    "glucose": 126
  }
]