[
  {
    "trend_arrow": "FLAT", 
    "display_time": "2016-10-31T12:43:13-07:00", 
    "noise": 1, 
    "direction": "Flat", 
    "system_time": "2016-10-31T18:36:34-07:00", 
    "sgv": 102, 
    "dateString": "2016-10-31T12:43:13-07:00", 
    "device": "openaps://indy-e1/cgm", 
    "unfiltered": 101696, 
    "rssi": 187, 
    "date": 1477942993000.0, 
    "filtered": 104656, 
    "type": "sgv", 
    "glucose": 102
  }, 
  {
    "trend_arrow": "FLAT", 
    "display_time": "2016-10-31T12:38:13-07:00", 
    "noise": 1, 
    "direction": "Flat", 
    "system_time": "2016-10-31T18:31:34-07:00", 
    "sgv": 102, 
    "dateString": "2016-10-31T12:38:13-07:00", 
    "device": "openaps://indy-e1/cgm", 
    "unfiltered": 101232, 
    "rssi": 199, 
    "date": 1477942693000.0, 
    "filtered": 108864, 
    "type": "sgv", 
    "glucose": 102
  }, 
  {
    "trend_arrow": "FLAT", 
    "display_time": "2016-10-31T12:33:13-07:00", 
    "noise": 1, 
    "direction": "Flat", 
    "system_time": "2016-10-31T18:26:34-07:00", 
    "sgv": 108, 
    "dateString": "2016-10-31T12:33:13-07:00", 
    "device": "openaps://indy-e1/cgm", 
    "unfiltered": 105920, 
    "rssi": 204, 
    "date": 1477942393000.0, 
    "filtered": 112320, 
    "type": "sgv", 
    "glucose": 108
  }, 
  {
    "trend_arrow": "FLAT", 
    "display_time": "2016-10-31T12:28:13-07:00", 
    "noise": 1, 
    "direction": "Flat", 
    "system_time": "2016-10-31T18:21:34-07:00", 
    "sgv": 112, 
    "dateString": "2016-10-31T12:28:13-07:00", 
    "device": "openaps://indy-e1/cgm", 
    "unfiltered": 109680, 
    "rssi": 213, 
    "date": 1477942093000.0, 
    "filtered": 113680, 
    "type": "sgv", 
    "glucose": 112
  }, 
  {
    "trend_arrow": "FLAT", 
    "display_time": "2016-10-31T12:23:13-07:00", 
    "noise": 1, 
    "direction": "Flat", 
    "system_time": "2016-10-31T18:16:34-07:00", 
    "sgv": 117, 
    "dateString": "2016-10-31T12:23:13-07:00", 
    "device": "openaps://indy-e1/cgm", 
    "unfiltered": 113760, 
    "rssi": 194, 
    "date": 1477941793000.0, 
    "filtered": 112992, 
    "type": "sgv", 
    "glucose": 117
  }, 
  {
    "trend_arrow": "FLAT", 
    "display_time": "2016-10-31T12:18:13-07:00", 
    "noise": 1, 
    "direction": "Flat", 
    "system_time": "2016-10-31T18:11:34-07:00", 
    "sgv": 117, 
    "dateString": "2016-10-31T12:18:13-07:00", 
    "device": "openaps://indy-e1/cgm", 
    "unfiltered": 113904, 
    "rssi": 213, 
    "date": 1477941493000.0, 
    "filtered": 111632, 
    "type": "sgv", 
    "glucose": 117
  }
]