[
  {
    "trend_arrow": "FLAT", 
    "display_time": "2016-10-31T03:23:15-07:00", 
    "noise": 1, 
    "direction": "Flat", 
    "system_time": "2016-10-31T09:16:36-07:00", 
    "sgv": 103, 
    "dateString": "2016-10-31T03:23:15-07:00", 
    "device": "openaps://indy-e1/cgm", 
    "unfiltered": 105248, 
    "rssi": 199, 
    "date": 1477909395000.0, 
    "filtered": 101360, 
    "type": "sgv", 
    "glucose": 103
  }, 
  {
    "trend_arrow": "FLAT", 
    "display_time": "2016-10-31T03:18:15-07:00", 
    "noise": 1, 
    "direction": "Flat", 
    "system_time": "2016-10-31T09:11:36-07:00", 
    "sgv": 100, 
    "dateString": "2016-10-31T03:18:15-07:00", 
    "device": "openaps://indy-e1/cgm", 
    "unfiltered": 101872, 
    "rssi": 200, 
    "date": 1477909095000.0, 
    "filtered": 99552, 
    "type": "sgv", 
    "glucose": 100
  }, 
  {
    "trend_arrow": "FLAT", 
    "display_time": "2016-10-31T03:13:15-07:00", 
    "noise": 1, 
    "direction": "Flat", 
    "system_time": "2016-10-31T09:06:36-07:00", 
    "sgv": 99, 
    "dateString": "2016-10-31T03:13:15-07:00", 
    "device": "openaps://indy-e1/cgm", 
    "unfiltered": 99440, 
    "rssi": 200, 
    "date": 1477908795000.0, 
    "filtered": 97168, 
    "type": "sgv", 
    "glucose": 99
  }, 
  {
    "trend_arrow": "FLAT", 
    "display_time": "2016-10-31T03:08:15-07:00", 
    "noise": 1, 
    "direction": "Flat", 
    "system_time": "2016-10-31T09:01:36-07:00", 
    "sgv": 96, 
    "dateString": "2016-10-31T03:08:15-07:00", 
    "device": "openaps://indy-e1/cgm", 
    "unfiltered": 98784, 
    "rssi": 200, 
    "date": 1477908495000.0, 
    "filtered": 94000, 
    "type": "sgv", 
    "glucose": 96
  }, 
  {
    "trend_arrow": "FLAT", 
    "display_time": "2016-10-31T03:03:16-07:00", 
    "noise": 1, 
    "direction": "Flat", 
    "system_time": "2016-10-31T08:56:36-07:00", 
    "sgv": 92, 
    "dateString": "2016-10-31T03:03:16-07:00", 
    "device": "openaps://indy-e1/cgm", 
    "unfiltered": 96512, 
    "rssi": 195, 
    "date": 1477908196000.0, 
    "filtered": 90704, 
    "type": "sgv", 
    "glucose": 92
  }, 
  {
    "trend_arrow": "FLAT", 
    "display_time": "2016-10-31T02:58:15-07:00", 
    "noise": 1, 
    "direction": "Flat", 
    "system_time": "2016-10-31T08:51:36-07:00", 
    "sgv": 87, 
    "dateString": "2016-10-31T02:58:15-07:00", 
    "device": "openaps://indy-e1/cgm", 
    "unfiltered": 92928, 
    "rssi": 451, 
    "date": 1477907895000.0, 
    "filtered": 88032, 
    "type": "sgv", 
    "glucose": 87
  }, 
  {
    "system_time": "2016-10-31T08:51:35-07:00", 
    "dateString": "2016-10-31T02:58:15-07:00", 
    "sgv": -1, 
    "display_time": "2016-10-31T02:58:15-07:00", 
    "device": "openaps://indy-e1/cgm", 
    "unfiltered": 89088, 
    "rssi": 196, 
    "date": 1477907895000.0, 
    "filtered": 86144, 
    "type": "sgv"
  }
]