[
  {
    "trend_arrow": "FLAT", 
    "display_time": "2016-10-21T16:08:45-07:00", 
    "noise": 1, 
    "system_time": "2016-10-21T22:02:22-07:00", 
    "direction": "Flat", 
    "sgv": 87, 
    "dateString": "2016-10-21T16:08:45-07:00", 
    "device": "openaps://indy-e1/cgm", 
    "unfiltered": 91472, 
    "rssi": 209, 
    "date": 1477091325000, 
    "filtered": 95296, 
    "type": "sgv", 
    "glucose": 87
  }, 
  {
    "trend_arrow": "FLAT", 
    "display_time": "2016-10-21T16:03:45-07:00", 
    "noise": 1, 
    "system_time": "2016-10-21T21:57:22-07:00", 
    "direction": "Flat", 
    "sgv": 91, 
    "dateString": "2016-10-21T16:03:45-07:00", 
    "device": "openaps://indy-e1/cgm", 
    "unfiltered": 94464, 
    "rssi": 196, 
    "date": 1477091025000, 
    "filtered": 97712, 
    "type": "sgv", 
    "glucose": 91
  }
]