[
  {
    "trend_arrow": "FLAT", 
    "display_time": "2016-10-22T09:18:42-07:00", 
    "noise": 1, 
    "system_time": "2016-10-22T15:12:18-07:00", 
    "direction": "Flat", 
    "sgv": 110, 
    "dateString": "2016-10-22T09:18:42-07:00", 
    "device": "openaps://indy-e1/cgm", 
    "unfiltered": 103616, 
    "rssi": 196, 
    "date": 1477153122000, 
    "filtered": 99920, 
    "type": "sgv", 
    "glucose": 110
  }, 
  {
    "trend_arrow": "FLAT", 
    "display_time": "2016-10-22T09:13:42-07:00", 
    "noise": 1, 
    "system_time": "2016-10-22T15:07:18-07:00", 
    "direction": "Flat", 
    "sgv": 107, 
    "dateString": "2016-10-22T09:13:42-07:00", 
    "device": "openaps://indy-e1/cgm", 
    "unfiltered": 101776, 
    "rssi": 195, 
    "date": 1477152822000, 
    "filtered": 96576, 
    "type": "sgv", 
    "glucose": 107
  }
]