[
  {
    "trend_arrow": "45_DOWN", 
    "display_time": "2016-10-18T16:29:00-07:00", 
    "noise": 1, 
    "direction": "FortyFiveDown", 
    "system_time": "2016-10-18T22:22:36-07:00", 
    "sgv": 93, 
    "dateString": "2016-10-18T16:29:00-07:00", 
    "device": "openaps://indy-e1/cgm", 
    "unfiltered": 96640, 
    "rssi": 196, 
    "date": 1476833340000.0, 
    "filtered": 107472, 
    "type": "sgv", 
    "glucose": 93
  }, 
  {
    "trend_arrow": "45_DOWN", 
    "display_time": "2016-10-18T16:24:00-07:00", 
    "noise": 1, 
    "direction": "FortyFiveDown", 
    "system_time": "2016-10-18T22:17:36-07:00", 
    "sgv": 104, 
    "dateString": "2016-10-18T16:24:00-07:00", 
    "device": "openaps://indy-e1/cgm", 
    "unfiltered": 104288, 
    "rssi": 185, 
    "date": 1476833040000.0, 
    "filtered": 112288, 
    "type": "sgv", 
    "glucose": 104
  }, 
  {
    "trend_arrow": "FLAT", 
    "display_time": "2016-10-18T16:19:00-07:00", 
    "noise": 1, 
    "direction": "Flat", 
    "system_time": "2016-10-18T22:12:36-07:00", 
    "sgv": 112, 
    "dateString": "2016-10-18T16:19:00-07:00", 
    "device": "openaps://indy-e1/cgm", 
    "unfiltered": 109888, 
    "rssi": 187, 
    "date": 1476832740000.0, 
    "filtered": 115728, 
    "type": "sgv", 
    "glucose": 112
  }, 
  {
    "trend_arrow": "FLAT", 
    "display_time": "2016-10-18T16:14:00-07:00", 
    "noise": 1, 
    "direction": "Flat", 
    "system_time": "2016-10-18T22:07:37-07:00", 
    "sgv": 119, 
    "dateString": "2016-10-18T16:14:00-07:00", 
    "device": "openaps://indy-e1/cgm", 
    "unfiltered": 114720, 
    "rssi": 199, 
    "date": 1476832440000.0, 
    "filtered": 118288, 
    "type": "sgv", 
    "glucose": 119
  }, 
  {
    "trend_arrow": "FLAT", 
    "display_time": "2016-10-18T16:09:00-07:00", 
    "noise": 1, 
    "direction": "Flat", 
    "system_time": "2016-10-18T22:02:36-07:00", 
    "sgv": 123, 
    "dateString": "2016-10-18T16:09:00-07:00", 
    "device": "openaps://indy-e1/cgm", 
    "unfiltered": 117248, 
    "rssi": 193, 
    "date": 1476832140000.0, 
    "filtered": 120016, 
    "type": "sgv", 
    "glucose": 123
  }, 
  {
    "trend_arrow": "FLAT", 
    "display_time": "2016-10-18T16:04:00-07:00", 
    "noise": 1, 
    "direction": "Flat", 
    "system_time": "2016-10-18T21:57:36-07:00", 
    "sgv": 125, 
    "dateString": "2016-10-18T16:04:00-07:00", 
    "device": "openaps://indy-e1/cgm", 
    "unfiltered": 118608, 
    "rssi": 197, 
    "date": 1476831840000.0, 
    "filtered": 120320, 
    "type": "sgv", 
    "glucose": 125
  }
]