[
  {
    "trend_arrow": "FLAT", 
    "display_time": "2016-10-20T02:38:53-07:00", 
    "noise": 1, 
    "system_time": "2016-10-20T08:32:29-07:00", 
    "direction": "Flat", 
    "sgv": 98, 
    "dateString": "2016-10-20T02:38:53-07:00", 
    "device": "openaps://indy-e1/cgm", 
    "unfiltered": 100192, 
    "rssi": 187, 
    "date": 1476956333000, 
    "filtered": 100752, 
    "type": "sgv", 
    "glucose": 98
  }, 
  {
    "trend_arrow": "FLAT", 
    "display_time": "2016-10-20T02:33:53-07:00", 
    "noise": 1, 
    "system_time": "2016-10-20T08:27:30-07:00", 
    "direction": "Flat", 
    "sgv": 98, 
    "dateString": "2016-10-20T02:33:53-07:00", 
    "device": "openaps://indy-e1/cgm", 
    "unfiltered": 100064, 
    "rssi": 189, 
    "date": 1476956033000, 
    "filtered": 102272, 
    "type": "sgv", 
    "glucose": 98
  }
]