[
  {
    "trend_arrow": "FLAT", 
    "display_time": "2016-10-25T02:58:37-07:00", 
    "noise": 1, 
    "system_time": "2016-10-25T09:46:28-07:00", 
    "direction": "Flat", 
    "sgv": 124, 
    "dateString": "2016-10-25T02:58:37-07:00", 
    "device": "openaps://indy-e1/cgm", 
    "unfiltered": 125696, 
    "rssi": 449, 
    "date": 1477389517000, 
    "filtered": 124656, 
    "type": "sgv", 
    "glucose": 124
  }, 
  {
    "trend_arrow": "FLAT", 
    "display_time": "2016-10-25T02:53:36-07:00", 
    "noise": 1, 
    "system_time": "2016-10-25T09:41:28-07:00", 
    "direction": "Flat", 
    "sgv": 123, 
    "dateString": "2016-10-25T02:53:36-07:00", 
    "device": "openaps://indy-e1/cgm", 
    "unfiltered": 124752, 
    "rssi": 195, 
    "date": 1477389216000, 
    "filtered": 124576, 
    "type": "sgv", 
    "glucose": 123
  }
]