[
  {
    "trend_arrow": "45_DOWN", 
    "display_time": "2016-10-25T18:23:33-07:00", 
    "noise": 1, 
    "direction": "FortyFiveDown", 
    "system_time": "2016-10-26T01:11:24-07:00", 
    "sgv": 108, 
    "dateString": "2016-10-25T18:23:33-07:00", 
    "device": "openaps://indy-e1/cgm", 
    "unfiltered": 117232, 
    "rssi": 214, 
    "date": 1477445013000.0, 
    "filtered": 124192, 
    "type": "sgv", 
    "glucose": 108
  }, 
  {
    "trend_arrow": "FLAT", 
    "display_time": "2016-10-25T18:18:33-07:00", 
    "noise": 1, 
    "direction": "Flat", 
    "system_time": "2016-10-26T01:06:24-07:00", 
    "sgv": 113, 
    "dateString": "2016-10-25T18:18:33-07:00", 
    "device": "openaps://indy-e1/cgm", 
    "unfiltered": 121456, 
    "rssi": 186, 
    "date": 1477444713000.0, 
    "filtered": 128720, 
    "type": "sgv", 
    "glucose": 113
  }, 
  {
    "trend_arrow": "FLAT", 
    "display_time": "2016-10-25T18:13:33-07:00", 
    "noise": 1, 
    "direction": "Flat", 
    "system_time": "2016-10-26T01:01:25-07:00", 
    "sgv": 118, 
    "dateString": "2016-10-25T18:13:33-07:00", 
    "device": "openaps://indy-e1/cgm", 
    "unfiltered": 126208, 
    "rssi": 193, 
    "date": 1477444413000.0, 
    "filtered": 132928, 
    "type": "sgv", 
    "glucose": 118
  }, 
  {
    "trend_arrow": "FLAT", 
    "display_time": "2016-10-25T18:08:33-07:00", 
    "noise": 1, 
    "direction": "Flat", 
    "system_time": "2016-10-26T00:56:24-07:00", 
    "sgv": 124, 
    "dateString": "2016-10-25T18:08:33-07:00", 
    "device": "openaps://indy-e1/cgm", 
    "unfiltered": 130976, 
    "rssi": 183, 
    "date": 1477444113000.0, 
    "filtered": 136736, 
    "type": "sgv", 
    "glucose": 124
  }, 
  {
    "trend_arrow": "FLAT", 
    "display_time": "2016-10-25T18:03:33-07:00", 
    "noise": 1, 
    "direction": "Flat", 
    "system_time": "2016-10-26T00:51:24-07:00", 
    "sgv": 128, 
    "dateString": "2016-10-25T18:03:33-07:00", 
    "device": "openaps://indy-e1/cgm", 
    "unfiltered": 134848, 
    "rssi": 201, 
    "date": 1477443813000.0, 
    "filtered": 139872, 
    "type": "sgv", 
    "glucose": 128
  }, 
  {
    "trend_arrow": "FLAT", 
    "display_time": "2016-10-25T17:58:33-07:00", 
    "noise": 1, 
    "direction": "Flat", 
    "system_time": "2016-10-26T00:46:25-07:00", 
    "sgv": 131, 
    "dateString": "2016-10-25T17:58:33-07:00", 
    "device": "openaps://indy-e1/cgm", 
    "unfiltered": 137696, 
    "rssi": 187, 
    "date": 1477443513000.0, 
    "filtered": 142112, 
    "type": "sgv", 
    "glucose": 131
  }
]