[
  {
    "trend_arrow": "FLAT", 
    "display_time": "2016-10-28T02:18:21-07:00", 
    "noise": 1, 
    "direction": "Flat", 
    "system_time": "2016-10-28T09:06:13-07:00", 
    "sgv": 249, 
    "dateString": "2016-10-28T02:18:21-07:00", 
    "device": "openaps://indy-e1/cgm", 
    "unfiltered": 272576, 
    "rssi": 185, 
    "date": 1477646301000.0, 
    "filtered": 270848, 
    "type": "sgv", 
    "glucose": 249
  }, 
  {
    "trend_arrow": "FLAT", 
    "display_time": "2016-10-28T02:13:21-07:00", 
    "noise": 1, 
    "direction": "Flat", 
    "system_time": "2016-10-28T09:01:13-07:00", 
    "sgv": 248, 
    "dateString": "2016-10-28T02:13:21-07:00", 
    "device": "openaps://indy-e1/cgm", 
    "unfiltered": 270720, 
    "rssi": 185, 
    "date": 1477646001000.0, 
    "filtered": 268480, 
    "type": "sgv", 
    "glucose": 248
  }, 
  {
    "trend_arrow": "FLAT", 
    "display_time": "2016-10-28T02:08:21-07:00", 
    "noise": 1, 
    "direction": "Flat", 
    "system_time": "2016-10-28T08:56:13-07:00", 
    "sgv": 247, 
    "dateString": "2016-10-28T02:08:21-07:00", 
    "device": "openaps://indy-e1/cgm", 
    "unfiltered": 270144, 
    "rssi": 186, 
    "date": 1477645701000.0, 
    "filtered": 265536, 
    "type": "sgv", 
    "glucose": 247
  }, 
  {
    "trend_arrow": "FLAT", 
    "display_time": "2016-10-28T02:03:21-07:00", 
    "noise": 1, 
    "direction": "Flat", 
    "system_time": "2016-10-28T08:51:13-07:00", 
    "sgv": 246, 
    "dateString": "2016-10-28T02:03:21-07:00", 
    "device": "openaps://indy-e1/cgm", 
    "unfiltered": 268800, 
    "rssi": 185, 
    "date": 1477645401000.0, 
    "filtered": 263360, 
    "type": "sgv", 
    "glucose": 246
  }, 
  {
    "trend_arrow": "FLAT", 
    "display_time": "2016-10-28T01:58:21-07:00", 
    "noise": 1, 
    "direction": "Flat", 
    "system_time": "2016-10-28T08:46:13-07:00", 
    "sgv": 242, 
    "dateString": "2016-10-28T01:58:21-07:00", 
    "device": "openaps://indy-e1/cgm", 
    "unfiltered": 265024, 
    "rssi": 183, 
    "date": 1477645101000.0, 
    "filtered": 262592, 
    "type": "sgv", 
    "glucose": 242
  }, 
  {
    "trend_arrow": "FLAT", 
    "display_time": "2016-10-28T01:53:21-07:00", 
    "noise": 1, 
    "direction": "Flat", 
    "system_time": "2016-10-28T08:41:13-07:00", 
    "sgv": 239, 
    "dateString": "2016-10-28T01:53:21-07:00", 
    "device": "openaps://indy-e1/cgm", 
    "unfiltered": 261920, 
    "rssi": 182, 
    "date": 1477644801000.0, 
    "filtered": 262528, 
    "type": "sgv", 
    "glucose": 239
  }
]