[
  {
    "trend_arrow": "45_UP", 
    "display_time": "2016-10-19T17:53:55-07:00", 
    "noise": 1, 
    "system_time": "2016-10-19T23:47:31-07:00", 
    "direction": "FortyFiveUp", 
    "sgv": 192, 
    "dateString": "2016-10-19T17:53:55-07:00", 
    "device": "openaps://indy-e1/cgm", 
    "unfiltered": 169696, 
    "rssi": 198, 
    "date": 1476924835000, 
    "filtered": 158656, 
    "type": "sgv", 
    "glucose": 192
  }, 
  {
    "trend_arrow": "45_UP", 
    "display_time": "2016-10-19T17:48:55-07:00", 
    "noise": 1, 
    "system_time": "2016-10-19T23:42:31-07:00", 
    "direction": "FortyFiveUp", 
    "sgv": 184, 
    "dateString": "2016-10-19T17:48:55-07:00", 
    "device": "openaps://indy-e1/cgm", 
    "unfiltered": 163808, 
    "rssi": 207, 
    "date": 1476924535000, 
    "filtered": 152672, 
    "type": "sgv", 
    "glucose": 184
  }
]