[
  {
    "trend_arrow": "FLAT", 
    "display_time": "2016-10-25T22:58:32-07:00", 
    "noise": 1, 
    "system_time": "2016-10-26T05:46:23-07:00", 
    "direction": "Flat", 
    "sgv": 110, 
    "dateString": "2016-10-25T22:58:32-07:00", 
    "device": "openaps://indy-e1/cgm", 
    "unfiltered": 121216, 
    "rssi": 188, 
    "date": 1477461512000, 
    "filtered": 118560, 
    "type": "sgv", 
    "glucose": 110
  }, 
  {
    "trend_arrow": "FLAT", 
    "display_time": "2016-10-25T22:53:32-07:00", 
    "noise": 1, 
    "system_time": "2016-10-26T05:41:23-07:00", 
    "direction": "Flat", 
    "sgv": 107, 
    "dateString": "2016-10-25T22:53:32-07:00", 
    "device": "openaps://indy-e1/cgm", 
    "unfiltered": 118720, 
    "rssi": 189, 
    "date": 1477461212000, 
    "filtered": 119648, 
    "type": "sgv", 
    "glucose": 107
  }
]