[
  {
    "trend_arrow": "NOT_COMPUTABLE", 
    "system_time": "2016-11-02T06:56:26", 
    "noise": 4, 
    "direction": "NOT COMPUTABLE", 
    "sgv": 10, 
    "display_time": "2016-11-02T01:03:06", 
    "date": 1478073786000.0, 
    "dateString": "2016-11-02T01:03:06", 
    "unfiltered": 66544, 
    "filtered": 48416, 
    "device": "openaps://indy-e1/cgm", 
    "rssi": 195, 
    "type": "sgv", 
    "glucose": 10
  }, 
  {
    "trend_arrow": "NOT_COMPUTABLE", 
    "system_time": "2016-11-02T06:51:26", 
    "noise": 4, 
    "direction": "NOT COMPUTABLE", 
    "sgv": 10, 
    "display_time": "2016-11-02T00:58:06", 
    "date": 1478073486000.0, 
    "dateString": "2016-11-02T00:58:06", 
    "unfiltered": 68944, 
    "filtered": 33192, 
    "device": "openaps://indy-e1/cgm", 
    "rssi": 196, 
    "type": "sgv", 
    "glucose": 10
  }, 
  {
    "trend_arrow": "NOT_COMPUTABLE", 
    "system_time": "2016-11-02T06:46:26", 
    "noise": 3, 
    "direction": "NOT COMPUTABLE", 
    "sgv": 57, 
    "display_time": "2016-11-02T00:53:06", 
    "date": 1478073186000.0, 
    "dateString": "2016-11-02T00:53:06", 
    "unfiltered": 49136, 
    "filtered": 29156, 
    "device": "openaps://indy-e1/cgm", 
    "rssi": 193, 
    "type": "sgv", 
    "glucose": 57
  }, 
  {
    "trend_arrow": "NOT_COMPUTABLE", 
    "system_time": "2016-11-02T06:41:26", 
    "noise": 3, 
    "direction": "NOT COMPUTABLE", 
    "sgv": 82, 
    "display_time": "2016-11-02T00:48:06", 
    "date": 1478072886000.0, 
    "dateString": "2016-11-02T00:48:06", 
    "unfiltered": 26804, 
    "filtered": 38288, 
    "device": "openaps://indy-e1/cgm", 
    "rssi": 189, 
    "type": "sgv", 
    "glucose": 82
  }, 
  {
    "trend_arrow": "NOT_COMPUTABLE", 
    "system_time": "2016-11-02T06:36:26", 
    "noise": 3, 
    "direction": "NOT COMPUTABLE", 
    "sgv": 118, 
    "display_time": "2016-11-02T00:43:06", 
    "date": 1478072586000.0, 
    "dateString": "2016-11-02T00:43:06", 
    "unfiltered": 26096, 
    "filtered": 51480, 
    "device": "openaps://indy-e1/cgm", 
    "rssi": 188, 
    "type": "sgv", 
    "glucose": 118
  }, 
  {
    "trend_arrow": "NOT_COMPUTABLE", 
    "system_time": "2016-11-02T06:31:26", 
    "noise": 3, 
    "direction": "NOT COMPUTABLE", 
    "sgv": 143, 
    "display_time": "2016-11-02T00:38:06", 
    "date": 1478072286000.0, 
    "dateString": "2016-11-02T00:38:06", 
    "unfiltered": 34576, 
    "filtered": 60448, 
    "device": "openaps://indy-e1/cgm", 
    "rssi": 185, 
    "type": "sgv", 
    "glucose": 143
  }
]