[
  {
    "trend_arrow": "FLAT", 
    "display_time": "2016-11-01T08:58:09-07:00", 
    "noise": 1, 
    "direction": "Flat", 
    "system_time": "2016-11-01T14:51:30-07:00", 
    "sgv": 151, 
    "dateString": "2016-11-01T08:58:09-07:00", 
    "device": "openaps://indy-e1/cgm", 
    "unfiltered": 121296, 
    "rssi": 221, 
    "date": 1478015889000.0, 
    "filtered": 123776, 
    "type": "sgv", 
    "glucose": 151
  }, 
  {
    "trend_arrow": "FLAT", 
    "display_time": "2016-11-01T08:53:09-07:00", 
    "noise": 1, 
    "direction": "Flat", 
    "system_time": "2016-11-01T14:46:30-07:00", 
    "sgv": 152, 
    "dateString": "2016-11-01T08:53:09-07:00", 
    "device": "openaps://indy-e1/cgm", 
    "unfiltered": 122064, 
    "rssi": 209, 
    "date": 1478015589000.0, 
    "filtered": 126112, 
    "type": "sgv", 
    "glucose": 152
  }, 
  {
    "trend_arrow": "FLAT", 
    "display_time": "2016-11-01T08:48:09-07:00", 
    "noise": 1, 
    "direction": "Flat", 
    "system_time": "2016-11-01T14:41:30-07:00", 
    "sgv": 160, 
    "dateString": "2016-11-01T08:48:09-07:00", 
    "device": "openaps://indy-e1/cgm", 
    "unfiltered": 127920, 
    "rssi": 208, 
    "date": 1478015289000.0, 
    "filtered": 129728, 
    "type": "sgv", 
    "glucose": 160
  }, 
  {
    "trend_arrow": "FLAT", 
    "display_time": "2016-11-01T08:43:09-07:00", 
    "noise": 1, 
    "direction": "Flat", 
    "system_time": "2016-11-01T14:36:30-07:00", 
    "sgv": 158, 
    "dateString": "2016-11-01T08:43:09-07:00", 
    "device": "openaps://indy-e1/cgm", 
    "unfiltered": 126112, 
    "rssi": 188, 
    "date": 1478014989000.0, 
    "filtered": 133888, 
    "type": "sgv", 
    "glucose": 158
  }, 
  {
    "trend_arrow": "FLAT", 
    "display_time": "2016-11-01T08:38:09-07:00", 
    "noise": 1, 
    "direction": "Flat", 
    "system_time": "2016-11-01T14:31:30-07:00", 
    "sgv": 163, 
    "dateString": "2016-11-01T08:38:09-07:00", 
    "device": "openaps://indy-e1/cgm", 
    "unfiltered": 130160, 
    "rssi": 200, 
    "date": 1478014689000.0, 
    "filtered": 136288, 
    "type": "sgv", 
    "glucose": 163
  }, 
  {
    "trend_arrow": "FLAT", 
    "display_time": "2016-11-01T08:33:09-07:00", 
    "noise": 1, 
    "direction": "Flat", 
    "system_time": "2016-11-01T14:26:30-07:00", 
    "sgv": 167, 
    "dateString": "2016-11-01T08:33:09-07:00", 
    "device": "openaps://indy-e1/cgm", 
    "unfiltered": 132672, 
    "rssi": 196, 
    "date": 1478014389000.0, 
    "filtered": 135360, 
    "type": "sgv", 
    "glucose": 167
  }
]